snp_stitch/__init__.py
snp_stitch/__main__.py
snp_stitch/model_training_functions.py
snp_stitch/variant_calling_functions.py
snp_stitch/models/ref_base_encoder.pkl
snp_stitch/models/regressor.pkl.gz
snp_stitch/models/tnc_encoder.pkl
snp_stitch-1.0.0.dist-info/licenses/LICENSE
snp_stitch-1.0.0.dist-info/METADATA
snp_stitch-1.0.0.dist-info/WHEEL
snp_stitch-1.0.0.dist-info/entry_points.txt
snp_stitch-1.0.0.dist-info/top_level.txt
snp_stitch-1.0.0.dist-info/RECORD
