Metadata-Version: 2.4
Name: snp_stitch
Version: 1.0.0
Summary: A lightweight variant caller for ONT data
Author-email: Zoe Vance <vancez@tcd.ie>
License-Expression: MIT
Project-URL: Homepage, https://github.com/ZoeVance/snp_stitch
Classifier: Programming Language :: Python :: 3
Classifier: Operating System :: OS Independent
License-File: LICENSE
Requires-Dist: scikit-learn
Requires-Dist: joblib
Requires-Dist: pysam
Requires-Dist: pandas
Requires-Dist: numpy
Dynamic: license-file
